README.txt
setup.cfg
setup.py
Products/__init__.py
Products.Clouseau.egg-info/PKG-INFO
Products.Clouseau.egg-info/SOURCES.txt
Products.Clouseau.egg-info/dependency_links.txt
Products.Clouseau.egg-info/entry_points.txt
Products.Clouseau.egg-info/namespace_packages.txt
Products.Clouseau.egg-info/not-zip-safe
Products.Clouseau.egg-info/requires.txt
Products.Clouseau.egg-info/top_level.txt
Products/Clouseau/LICENSE.GPL
Products/Clouseau/README.txt
Products/Clouseau/__init__.py
Products/Clouseau/bootstrap.py
Products/Clouseau/clouseau.jpg
Products/Clouseau/config.py
Products/Clouseau/configure.zcml
Products/Clouseau/introspect.py
Products/Clouseau/output.py
Products/Clouseau/permissions.py
Products/Clouseau/sessions.py
Products/Clouseau/version.txt
Products/Clouseau/i18n/clouseau-es.po
Products/Clouseau/i18n/clouseau-plone-es.po
Products/Clouseau/i18n/clouseau-plone.pot
Products/Clouseau/i18n/clouseau.pot
Products/Clouseau/profiles/default/actionicons.xml
Products/Clouseau/profiles/default/actions.xml
Products/Clouseau/profiles/default/controlpanel.xml
Products/Clouseau/profiles/default/cssregistry.xml
Products/Clouseau/profiles/default/jsregistry.xml
Products/Clouseau/profiles/default/metadata.xml
Products/Clouseau/profiles/default/skins.xml
Products/Clouseau/profiles/default/toolset.xml
Products/Clouseau/saved/README.txt
Products/Clouseau/saved/global/tool-shortcuts.py
Products/Clouseau/saved/local/hello-world.py
Products/Clouseau/skins/Clouseau/SyntaxHighlighter.css
Products/Clouseau/skins/Clouseau/button_cancel.png
Products/Clouseau/skins/Clouseau/clouseau-frame.css
Products/Clouseau/skins/Clouseau/clouseau.css.dtml
Products/Clouseau/skins/Clouseau/clouseau.png
Products/Clouseau/skins/Clouseau/clouseau_header.pt
Products/Clouseau/skins/Clouseau/clouseau_help.pt
Products/Clouseau/skins/Clouseau/clouseau_list.pt
Products/Clouseau/skins/Clouseau/clouseau_load.pt
Products/Clouseau/skins/Clouseau/clouseau_macros.pt
Products/Clouseau/skins/Clouseau/clouseau_minimal.pt
Products/Clouseau/skins/Clouseau/clouseau_trigger.js
Products/Clouseau/skins/Clouseau/clouseau_view.cpt
Products/Clouseau/skins/Clouseau/process.js
Products/Clouseau/skins/Clouseau/save_all.png
Products/Clouseau/skins/Clouseau/shBrushPython.js
Products/Clouseau/skins/Clouseau/shClouseau.js
Products/Clouseau/skins/Clouseau/shCore.js
