Metadata-Version: 1.0
Name: Products.Clouseau
Version: 1.0
Summary: An Ajax based Zope/Python prompt for Plone
Home-page: http://plone.org/products/clouseau
Author: Andy McKay
Author-email: andy@clearwind.ca
License: GPL
Keywords: Plone Clouseau AJAX
Platform: UNKNOWN
Classifier: Programming Language :: Python
Classifier: Topic :: Software Development :: Libraries :: Python Modules
Classifier: Framework :: Plone
